LICENSE
README.md
setup.cfg
setup.py
logholm/__init__.py
logholm/main.py
logholm/properties.py
logholm.egg-info/PKG-INFO
logholm.egg-info/SOURCES.txt
logholm.egg-info/dependency_links.txt
logholm.egg-info/not-zip-safe
logholm.egg-info/top_level.txt