Metadata-Version: 2.1
Name: logholm
Version: 1.0.3
Summary: The most powerful and easy to code logging library.
Home-page: https://github.com/stockholmdev/logholm-python
Author-email: stockholmdev@protonmail.com
License: MIT
Platform: UNKNOWN
License-File: LICENSE
